noneapi/__init__.py
noneapi/containers.py
noneapi/docs.py
noneapi/events.py
noneapi/exceptions.py
noneapi/handlers.py
noneapi/protocols.py
noneapi/proxies.py
noneapi/rpc.py
noneapi/serializers.py
noneapi/servers.py
noneapi/services.py
noneapi/transports.py
noneapi/validations.py
noneapi-0.1.7.dist-info/LICENSE.md
noneapi-0.1.7.dist-info/METADATA
noneapi-0.1.7.dist-info/WHEEL
noneapi-0.1.7.dist-info/top_level.txt
noneapi-0.1.7.dist-info/RECORD
