Metadata-Version: 2.1
Name: noneapi
Version: 0.1.7
Summary: Micro RPC framework based on ZeroMQ for building distributed systems
Author-email: Denys Rozlomii <eighty.eighth.inc@gmail.com>
License: MIT
Project-URL: repository, https://github.com/EightyEighth/noneapi
Classifier: Development Status :: 4 - Beta
Classifier: Intended Audience :: Developers
Classifier: License :: OSI Approved :: MIT License
Classifier: Programming Language :: Python :: 3.10
Classifier: Programming Language :: Python :: 3.11
Classifier: Programming Language :: Python :: 3.12
License-File: LICENSE.md
Requires-Dist: pyzmq==26.2.0
Requires-Dist: loguru==0.7.2
Requires-Dist: gevent==24.10.1
Requires-Dist: pdoc==14.7.0
Requires-Dist: pydantic==2.9.2
Requires-Dist: orjson==3.10.7
Provides-Extra: dev
Requires-Dist: pytest; extra == "dev"
Requires-Dist: flake8; extra == "dev"
Requires-Dist: black; extra == "dev"
Requires-Dist: mypy; extra == "dev"
Requires-Dist: isort; extra == "dev"
Requires-Dist: pytest-cov; extra == "dev"
Requires-Dist: requests; extra == "dev"
